[
  {
    "type": "constructor",
    "inputs": [
      {
        "name": "_identityRegistry",
        "type": "address",
        "internalType": "address"
      }
    ],
    "stateMutability": "nonpayable"
  },
  {
    "type": "function",
    "name": "getAgentValidations",
    "inputs": [
      {
        "name": "agentId",
        "type": "uint256",
        "internalType": "uint256"
      }
    ],
    "outputs": [
      {
        "name": "requestHashes",
        "type": "bytes32[]",
        "internalType": "bytes32[]"
      }
    ],
    "stateMutability": "view"
  },
  {
    "type": "function",
    "name": "getIdentityRegistry",
    "inputs": [],
    "outputs": [
      {
        "name": "registry",
        "type": "address",
        "internalType": "address"
      }
    ],
    "stateMutability": "view"
  },
  {
    "type": "function",
    "name": "getRequest",
    "inputs": [
      {
        "name": "requestHash",
        "type": "bytes32",
        "internalType": "bytes32"
      }
    ],
    "outputs": [
      {
        "name": "validatorAddress",
        "type": "address",
        "internalType": "address"
      },
      {
        "name": "agentId",
        "type": "uint256",
        "internalType": "uint256"
      },
      {
        "name": "requestUri",
        "type": "string",
        "internalType": "string"
      },
      {
        "name": "timestamp",
        "type": "uint256",
        "internalType": "uint256"
      }
    ],
    "stateMutability": "view"
  },
  {
    "type": "function",
    "name": "getSummary",
    "inputs": [
      {
        "name": "agentId",
        "type": "uint256",
        "internalType": "uint256"
      },
      {
        "name": "validatorAddresses",
        "type": "address[]",
        "internalType": "address[]"
      },
      {
        "name": "tag",
        "type": "bytes32",
        "internalType": "bytes32"
      }
    ],
    "outputs": [
      {
        "name": "count",
        "type": "uint64",
        "internalType": "uint64"
      },
      {
        "name": "avgResponse",
        "type": "uint8",
        "internalType": "uint8"
      }
    ],
    "stateMutability": "view"
  },
  {
    "type": "function",
    "name": "getValidationStatus",
    "inputs": [
      {
        "name": "requestHash",
        "type": "bytes32",
        "internalType": "bytes32"
      }
    ],
    "outputs": [
      {
        "name": "validatorAddress",
        "type": "address",
        "internalType": "address"
      },
      {
        "name": "agentId",
        "type": "uint256",
        "internalType": "uint256"
      },
      {
        "name": "response",
        "type": "uint8",
        "internalType": "uint8"
      },
      {
        "name": "tag",
        "type": "bytes32",
        "internalType": "bytes32"
      },
      {
        "name": "lastUpdate",
        "type": "uint256",
        "internalType": "uint256"
      }
    ],
    "stateMutability": "view"
  },
  {
    "type": "function",
    "name": "getValidatorRequests",
    "inputs": [
      {
        "name": "validatorAddress",
        "type": "address",
        "internalType": "address"
      }
    ],
    "outputs": [
      {
        "name": "requestHashes",
        "type": "bytes32[]",
        "internalType": "bytes32[]"
      }
    ],
    "stateMutability": "view"
  },
  {
    "type": "function",
    "name": "identityRegistry",
    "inputs": [],
    "outputs": [
      {
        "name": "",
        "type": "address",
        "internalType": "contract IdentityRegistry"
      }
    ],
    "stateMutability": "view"
  },
  {
    "type": "function",
    "name": "requestExists",
    "inputs": [
      {
        "name": "requestHash",
        "type": "bytes32",
        "internalType": "bytes32"
      }
    ],
    "outputs": [
      {
        "name": "exists",
        "type": "bool",
        "internalType": "bool"
      }
    ],
    "stateMutability": "view"
  },
  {
    "type": "function",
    "name": "validationRequest",
    "inputs": [
      {
        "name": "validatorAddress",
        "type": "address",
        "internalType": "address"
      },
      {
        "name": "agentId",
        "type": "uint256",
        "internalType": "uint256"
      },
      {
        "name": "requestUri",
        "type": "string",
        "internalType": "string"
      },
      {
        "name": "requestHash",
        "type": "bytes32",
        "internalType": "bytes32"
      }
    ],
    "outputs": [],
    "stateMutability": "nonpayable"
  },
  {
    "type": "function",
    "name": "validationResponse",
    "inputs": [
      {
        "name": "requestHash",
        "type": "bytes32",
        "internalType": "bytes32"
      },
      {
        "name": "response",
        "type": "uint8",
        "internalType": "uint8"
      },
      {
        "name": "responseUri",
        "type": "string",
        "internalType": "string"
      },
      {
        "name": "responseHash",
        "type": "bytes32",
        "internalType": "bytes32"
      },
      {
        "name": "tag",
        "type": "bytes32",
        "internalType": "bytes32"
      }
    ],
    "outputs": [],
    "stateMutability": "nonpayable"
  },
  {
    "type": "event",
    "name": "ValidationRequest",
    "inputs": [
      {
        "name": "validatorAddress",
        "type": "address",
        "indexed": true,
        "internalType": "address"
      },
      {
        "name": "agentId",
        "type": "uint256",
        "indexed": true,
        "internalType": "uint256"
      },
      {
        "name": "requestUri",
        "type": "string",
        "indexed": false,
        "internalType": "string"
      },
      {
        "name": "requestHash",
        "type": "bytes32",
        "indexed": true,
        "internalType": "bytes32"
      }
    ],
    "anonymous": false
  },
  {
    "type": "event",
    "name": "ValidationResponse",
    "inputs": [
      {
        "name": "validatorAddress",
        "type": "address",
        "indexed": true,
        "internalType": "address"
      },
      {
        "name": "agentId",
        "type": "uint256",
        "indexed": true,
        "internalType": "uint256"
      },
      {
        "name": "requestHash",
        "type": "bytes32",
        "indexed": true,
        "internalType": "bytes32"
      },
      {
        "name": "response",
        "type": "uint8",
        "indexed": false,
        "internalType": "uint8"
      },
      {
        "name": "responseUri",
        "type": "string",
        "indexed": false,
        "internalType": "string"
      },
      {
        "name": "responseHash",
        "type": "bytes32",
        "indexed": false,
        "internalType": "bytes32"
      },
      {
        "name": "tag",
        "type": "bytes32",
        "indexed": false,
        "internalType": "bytes32"
      }
    ],
    "anonymous": false
  }
]